netimpact/__init__.py
netimpact/admitad.py
netimpact/awin.py
netimpact/impact.py
netimpact/linkshare.py
netimpact/netimpact.py
netimpact/network.py
netimpact-0.1.dist-info/LICENSE
netimpact-0.1.dist-info/METADATA
netimpact-0.1.dist-info/WHEEL
netimpact-0.1.dist-info/entry_points.txt
netimpact-0.1.dist-info/top_level.txt
netimpact-0.1.dist-info/RECORD
