Metadata-Version: 2.1
Name: netimpact
Version: 0.1
Summary: UNKNOWN
Home-page: UNKNOWN
Author: UNKNOWN
Author-email: UNKNOWN
License: UNKNOWN
Platform: UNKNOWN
Requires-Dist: Click
Requires-Dist: requests
Requires-Dist: toml
